README.md
setup.py
src/vdk/plugin/structlog/constants.py
src/vdk/plugin/structlog/filters.py
src/vdk/plugin/structlog/formatters.py
src/vdk/plugin/structlog/log_level_utils.py
src/vdk/plugin/structlog/structlog_config.py
src/vdk/plugin/structlog/structlog_plugin.py
src/vdk/plugin/structlog/syslog_config.py
src/vdk_structlog.egg-info/PKG-INFO
src/vdk_structlog.egg-info/SOURCES.txt
src/vdk_structlog.egg-info/dependency_links.txt
src/vdk_structlog.egg-info/entry_points.txt
src/vdk_structlog.egg-info/requires.txt
src/vdk_structlog.egg-info/top_level.txt
tests/test_structlog.py